{"slug": "cornwall", "provider": "City of Cornwall", "license_name": "Open Government Licence - City of Cornwall", "row_count": 20618, "last_date": "2026-07-01", "added": 3, "removed": 1, "modified": 0, "highlight": "", "has_changes": true, "report_count": 11, "compared_fields": ["Street number (ST_NUMBER)", "Street name (STREET)", "Unit (UNIT)", "Full address (ADDRESS)", "Coordinates (latitude, longitude)", "ADD_TYPE", "AddressID", "BUILDING", "CITY", "COUNTRY", "DIRECTION", "FLOOR", "LAST_EDIT", "POLY_ID", "POSTAL", "PROVINCE", "STREET_LNG", "SUFFIX"], "ignored_fields": [], "no_changes": false, "hull": {"type": "Polygon", "coordinates": [[[-74.82325, 45.03385], [-74.82649, 45.03663], [-74.75216, 45.06791], [-74.71372, 45.08317], [-74.7079, 45.08352], [-74.67346, 45.04182], [-74.6689, 45.03452], [-74.67093, 45.02954], [-74.69785, 45.01808], [-74.73716, 45.01045], [-74.76554, 45.01036], [-74.77394, 45.01067], [-74.78055, 45.01265], [-74.78279, 45.01685], [-74.80112, 45.03832], [-74.82325, 45.03385]]]}}