{"slug": "ottawa", "provider": "City of Ottawa", "license_name": "Open Government Licence \u2013 City of Ottawa 2.0", "row_count": 402886, "last_date": "2026-07-01", "added": 3, "removed": 0, "modified": 8, "highlight": "", "has_changes": true, "report_count": 14, "compared_fields": ["Street number (ADDRNUM)", "Street name (FULLNAME)", "Unit (UNITID)", "Full address (FULLADDR)", "Coordinates (latitude, longitude)", "ADDRTYPE", "PI_MUNICIPAL_ADDRESS_ID", "QUALIFIER"], "ignored_fields": ["CREATED_DATE", "MODIFIED_DATE"], "no_changes": false, "hull": {"type": "Polygon", "coordinates": [[[-76.26052, 45.34892], [-76.3252, 45.42102], [-76.2826, 45.46316], [-76.18771, 45.51457], [-76.13145, 45.51223], [-76.0928, 45.50843], [-75.99537, 45.4767], [-75.68323, 45.45488], [-75.4598, 45.51433], [-75.44249, 45.51697], [-75.38441, 45.52139], [-75.35135, 45.51256], [-75.27986, 45.35363], [-75.44229, 45.14752], [-75.65406, 45.06558], [-75.73537, 45.01503], [-75.78816, 44.98769], [-75.81533, 44.97554], [-75.96821, 45.11658], [-76.21152, 45.30427], [-76.26052, 45.34892]]]}}