{"slug": "chatham-kent", "provider": "Municipality of Chatham-Kent", "license_name": "Not identified", "row_count": 58809, "last_date": "2026-07-24", "added": 61, "removed": 373, "modified": 0, "highlight": "", "has_changes": true, "report_count": 12, "compared_fields": ["Street number (ADDRESS_NUMBER)", "Street name (STREET_NAME)", "Full address (BASE_ADDRESS)", "Coordinates (latitude, longitude)", "ADDRESS_ID", "COMMUNITY_NAME", "COMMUNITY_TYPE", "GISID", "STREET_DIR"], "ignored_fields": [], "no_changes": false, "hull": {"type": "Polygon", "coordinates": [[[-82.4696, 42.59414], [-82.48196, 42.63119], [-82.21124, 42.62582], [-81.97756, 42.65025], [-81.9081, 42.64933], [-81.86068, 42.64159], [-81.84768, 42.63619], [-81.69325, 42.47894], [-81.69608, 42.45544], [-81.84447, 42.26662], [-81.91766, 42.25881], [-82.13877, 42.22946], [-82.18119, 42.20714], [-82.23962, 42.18161], [-82.46479, 42.06242], [-82.46697, 42.0945], [-82.45799, 42.1559], [-82.4387, 42.31194], [-82.43535, 42.51007], [-82.4696, 42.59414]]]}}