{"slug": "milton", "provider": "Town of Milton", "license_name": "Not identified", "row_count": 46324, "last_date": "2026-06-14", "added": 0, "removed": 0, "modified": 0, "highlight": "", "has_changes": true, "report_count": 3, "compared_fields": ["Street number (ADDRESS_NUM)", "Street name (STREET_NAME)", "Unit (UNIT_NUMBER)", "Full address (FULL_ADDRESS)", "Coordinates (latitude, longitude)", "ADU", "ADU_UNIT_NO", "ASSIGNED_BY", "Address_ID", "BLOCK", "DESCRIPTION", "DISPLAY_NAME", "GEOSTNAME", "HISTORY", "LABEL_ANGLE", "LOT", "POLL", "PROP_RSN", "STATUS", "STREET_TYPE", "ST_DIR_SUFFIX", "SUBDIVISION_PLAN", "WARD"], "ignored_fields": [], "no_changes": false, "hull": {"type": "Polygon", "coordinates": [[[-80.1451, 43.55778], [-80.15194, 43.56798], [-80.09651, 43.61839], [-80.08477, 43.62728], [-80.0162, 43.57878], [-79.89977, 43.55745], [-79.82026, 43.56902], [-79.79097, 43.57096], [-79.7847, 43.57014], [-79.75905, 43.55341], [-79.7351, 43.53578], [-79.73323, 43.53364], [-79.73195, 43.52783], [-79.79807, 43.44812], [-79.81341, 43.43761], [-79.83335, 43.44957], [-79.94408, 43.43155], [-79.95215, 43.42426], [-79.96467, 43.42204], [-80.13046, 43.54114], [-80.1451, 43.55778]]]}}